{
	"action": [
		{
			"name": "Attack",
			"source": "PHB",
			"system": {
				"target.value": 1,
				"target.type": "creature"
			}
		},
		{
			"name": "Climb onto a Bigger Creature",
			"source": "DMG",
			"system": {
				"target.value": 1,
				"target.type": "creature"
			}
		},
		{
			"name": "Disarm",
			"source": "DMG",
			"system": {
				"target.value": 1,
				"target.type": "creature"
			}
		},
		{
			"name": "Grapple",
			"source": "PHB",
			"system": {
				"target.value": 1,
				"target.type": "creature"
			}
		},
		{
			"name": "Mark",
			"source": "DMG",
			"system": {
				"target.value": 1,
				"target.type": "creature"
			}
		},
		{
			"name": "Opportunity Attack",
			"source": "PHB",
			"system": {
				"target.value": 1,
				"target.type": "creature"
			}
		},
		{
			"name": "Overrun",
			"source": "DMG",
			"system": {
				"target.value": 1,
				"target.type": "creature"
			}
		},
		{
			"name": "Shove",
			"source": "PHB",
			"system": {
				"target.value": 1,
				"target.type": "creature"
			}
		},
		{
			"name": "Shove Aside",
			"source": "DMG",
			"system": {
				"target.value": 1,
				"target.type": "creature"
			}
		},
		{
			"name": "Tumble",
			"source": "DMG",
			"system": {
				"target.value": 1,
				"target.type": "creature"
			}
		}
	]
}
